decide_analysis/__init__.py
decide_analysis/core.py
decide_analysis/get_data.py
decide_analysis/host.py
decide_analysis/post_trials.py
decide_analysis-2.2.0.dist-info/COPYING
decide_analysis-2.2.0.dist-info/METADATA
decide_analysis-2.2.0.dist-info/WHEEL
decide_analysis-2.2.0.dist-info/entry_points.txt
decide_analysis-2.2.0.dist-info/top_level.txt
decide_analysis-2.2.0.dist-info/RECORD
